MANIFEST.in
README.md
pyproject.toml
setup.py
amuse_brutus.egg-info/PKG-INFO
amuse_brutus.egg-info/SOURCES.txt
amuse_brutus.egg-info/dependency_links.txt
amuse_brutus.egg-info/requires.txt
amuse_brutus.egg-info/top_level.txt
src/amuse/community/brutus/Makefile
src/amuse/community/brutus/__init__.py
src/amuse/community/brutus/_version.py
src/amuse/community/brutus/interface.cc
src/amuse/community/brutus/interface.py
src/amuse/community/brutus/mpfrc++/mpreal.h
src/amuse/community/brutus/src/Brutus.cpp
src/amuse/community/brutus/src/Brutus.h
src/amuse/community/brutus/src/Bulirsch_Stoer.cpp
src/amuse/community/brutus/src/Bulirsch_Stoer.h
src/amuse/community/brutus/src/Cluster.cpp
src/amuse/community/brutus/src/Cluster.h
src/amuse/community/brutus/src/Star.cpp
src/amuse/community/brutus/src/Star.h
src/amuse/community/brutus/src/main.cpp
src/amuse/community/brutus/src/makefile
support/__init__.py
support/classifiers.py
support/config.py
support/generate_main.py
support/getsp.class
support/getsp.java
support/misc.py
support/setup_codes.py
support/version.py